mllib/Fcls.py
mllib/__init__.py
mllib/src/theory.yaml
mllib_exam-0.1.1.dist-info/METADATA
mllib_exam-0.1.1.dist-info/WHEEL
mllib_exam-0.1.1.dist-info/top_level.txt
mllib_exam-0.1.1.dist-info/RECORD
